README.md
setup.py
yggtorrentscraper.egg-info/PKG-INFO
yggtorrentscraper.egg-info/SOURCES.txt
yggtorrentscraper.egg-info/dependency_links.txt
yggtorrentscraper.egg-info/requires.txt
yggtorrentscraper.egg-info/top_level.txt
yts/__init__.py
yts/categories.py
yts/torrent.py
yts/yts.py
yts/yts_old.py
yts/yts_selenium.py
yts/tests/__init__.py
yts/tests/test_change_tld.py
yts/tests/test_download.py
yts/tests/test_extract_details.py
yts/tests/test_login.py
yts/tests/test_logout.py
yts/tests/test_most_completed.py
yts/tests/test_search.py
yts/tests/test_torrent.py