Metadata-Version: 2.1
Name: yggtorrentscraper
Version: 1.2.9
Summary: Scraper for YggTorrent
Home-page: https://github.com/Harkame/YggTorrentDownloader
Author: Harkame
License: UNKNOWN
Platform: UNKNOWN
Classifier: Programming Language :: Python
Classifier: License :: OSI Approved
Classifier: Operating System :: OS Independent
Requires-Python: >=3.6
